bam2tensor/__init__.py
bam2tensor/__main__.py
bam2tensor/embedding.py
bam2tensor/functions.py
bam2tensor/py.typed
bam2tensor-1.5.dist-info/METADATA
bam2tensor-1.5.dist-info/WHEEL
bam2tensor-1.5.dist-info/entry_points.txt
bam2tensor-1.5.dist-info/licenses/LICENSE
bam2tensor-1.5.dist-info/RECORD
