Metadata-Version: 2.4
Name: bam2tensor
Version: 1.5
Summary: Bam2Tensor
License: MIT
License-File: LICENSE
Author: Nick Semenkovich
Author-email: semenko@alum.mit.edu
Requires-Python: >=3.10,<4.0
Classifier: Development Status :: 4 - Beta
Classifier: License :: OSI Approved :: MIT License
Classifier: Programming Language :: Python :: 3
Classifier: Programming Language :: Python :: 3.10
Classifier: Programming Language :: Python :: 3.11
Classifier: Programming Language :: Python :: 3.12
Classifier: Programming Language :: Python :: 3.13
Classifier: Programming Language :: Python :: 3.14
Requires-Dist: biopython (>=1.81)
Requires-Dist: click (>=8.0.1)
Requires-Dist: numpy (>=1.26.0)
Requires-Dist: pysam (>=0.22.0)
Requires-Dist: scipy (>=1.11.4)
Requires-Dist: tqdm (>=4.66.1)
Project-URL: Changelog, https://github.com/mcwdsi/bam2tensor/releases
Project-URL: Documentation, https://mcwdsi.github.io/bam2tensor
Project-URL: Homepage, https://github.com/mcwdsi/bam2tensor
Project-URL: Repository, https://github.com/mcwdsi/bam2tensor
